{"statistical_data": {"friends_num": 5, "active_num": 3, "error_num": 2, "article_num": 7, "last_updated_time": "2022-12-10 16:32:56"}, "article_data": [{"floor": 1, "title": "\u7c73\u5bb6\u7eaf\u51c0\u5f0f\u667a\u80fd\u52a0\u6e7f\u5668 2 Lite \u4f53\u9a8c\u6587", "created": "2022-12-09", "updated": "2022-12-09", "link": "https://dusays.com/533/", "author": "\u675c\u8001\u5e08\u8bf4", "avatar": "https://cdn.dusays.com/avatar.png"}, {"floor": 2, "title": "\u611f\u8c22\u5317\u95e8\u6e05\u71d5\u7ae5\u9774\u5e2e\u5fd9\u5f00\u53d1\u7684\u4e91\u5b58\u6863\u63d2\u4ef6", "created": "2022-12-06", "updated": "2022-12-06", "link": "https://dusays.com/532/", "author": "\u675c\u8001\u5e08\u8bf4", "avatar": "https://cdn.dusays.com/avatar.png"}, {"floor": 3, "title": "\u675c\u8001\u5e08\u8bf4\u65d7\u4e0b\u5934\u50cf\u751f\u6210\u5e73\u53f0", "created": "2022-12-03", "updated": "2022-12-03", "link": "https://dusays.com/531/", "author": "\u675c\u8001\u5e08\u8bf4", "avatar": "https://cdn.dusays.com/avatar.png"}, {"floor": 4, "title": "\u675c\u8001\u5e08\u8bf4\u65d7\u4e0b\u670d\u52a1\u5e73\u53f0\u6c47\u603b", "created": "2022-11-30", "updated": "2022-11-30", "link": "https://dusays.com/530/", "author": "\u675c\u8001\u5e08\u8bf4", "avatar": "https://cdn.dusays.com/avatar.png"}, {"floor": 5, "title": "\u6797\u6797\u5c0f\u76c6\u53cb\u63d0\u4f9b\u516c\u76ca Umami \u7edf\u8ba1\u670d\u52a1", "created": "2022-11-27", "updated": "2022-11-27", "link": "https://dusays.com/529/", "author": "\u675c\u8001\u5e08\u8bf4", "avatar": "https://cdn.dusays.com/avatar.png"}, {"floor": 6, "title": "\u642d\u5efa\u73af\u5883\u4e0e\u90e8\u7f72\u535a\u5ba2\u7684\u6700\u7b80\u4fbf\u65b9\u6cd5", "created": "2022-11-26", "updated": "2022-11-26", "link": "https://xaoxuu.com/blog/20221126/", "author": "xaoxuu", "avatar": "https://bu.dusays.com/2021/09/24/2f74810ceb3d3.png"}, {"floor": 7, "title": "\u6d45\u5c1d GitHub Codespaces", "created": "2022-11-21", "updated": "2022-11-21", "link": "https://xaoxuu.com/blog/20221121/", "author": "xaoxuu", "avatar": "https://bu.dusays.com/2021/09/24/2f74810ceb3d3.png"}]}